prjct/__init__.py
prjct/cli.py
prjct/config.py
prjct/descriptions.py
prjct/exceptions.py
prjct/multi_source.py
prjct/sphinx.py
prjct/todo_export.py
prjct/util.py
prjct/_vendor/__init__.py
prjct/_vendor/jrnl/DayOneJournal.py
prjct/_vendor/jrnl/EncryptedJournal.py
prjct/_vendor/jrnl/Entry.py
prjct/_vendor/jrnl/Journal.py
prjct/_vendor/jrnl/__init__.py
prjct/_vendor/jrnl/__main__.py
prjct/_vendor/jrnl/cli.py
prjct/_vendor/jrnl/export.py
prjct/_vendor/jrnl/install.py
prjct/_vendor/jrnl/time.py
prjct/_vendor/jrnl/upgrade.py
prjct/_vendor/jrnl/util.py
prjct/_vendor/jrnl/plugins/__init__.py
prjct/_vendor/jrnl/plugins/jrnl_importer.py
prjct/_vendor/jrnl/plugins/json_exporter.py
prjct/_vendor/jrnl/plugins/markdown_exporter.py
prjct/_vendor/jrnl/plugins/prjct_exporter.py
prjct/_vendor/jrnl/plugins/tag_exporter.py
prjct/_vendor/jrnl/plugins/template.py
prjct/_vendor/jrnl/plugins/template_exporter.py
prjct/_vendor/jrnl/plugins/text_exporter.py
prjct/_vendor/jrnl/plugins/util.py
prjct/_vendor/jrnl/plugins/xml_exporter.py
prjct/_vendor/jrnl/plugins/yaml_exporter.py
prjct-0.6.0.dist-info/DESCRIPTION.rst
prjct-0.6.0.dist-info/METADATA
prjct-0.6.0.dist-info/RECORD
prjct-0.6.0.dist-info/WHEEL
prjct-0.6.0.dist-info/entry_points.txt
prjct-0.6.0.dist-info/metadata.json
prjct-0.6.0.dist-info/top_level.txt
test/__init__.py
test/test_list_filtering.py
test/test_sphinx.py
test/test_todo_export.py
vendor_src/__init__.py
vendor_src/jrnl/__init__.py
