Metadata-Version: 2.0
Name: prjct
Version: 0.6.0
Summary: Project Management for Living Life
Home-page: https://github.com/MinchinWeb/prjct
Author: William Minchin
Author-email: w_minchin@hotmail.com
License: MIT License
Platform: any
Classifier: Development Status :: 3 - Alpha
Classifier: Programming Language :: Python :: 3
Classifier: Programming Language :: Python :: 3.6
Classifier: Environment :: Plugins
Classifier: Environment :: Web Environment
Classifier: Intended Audience :: Developers
Classifier: Intended Audience :: End Users/Desktop
Classifier: Natural Language :: English
Classifier: Operating System :: OS Independent
Classifier: Topic :: Documentation
Classifier: Topic :: Office/Business
Classifier: Topic :: Software Development :: Libraries :: Python Modules
Classifier: Topic :: Text Processing
Classifier: License :: OSI Approved :: MIT License
Requires-Dist: cloudmesh-timestring
Requires-Dist: topydo (>=0.11.0)
Requires-Dist: click
Requires-Dist: invoke
Requires-Dist: winshell
Requires-Dist: pypiwin32
Requires-Dist: appdirs
Requires-Dist: markdown
Requires-Dist: minchin.pelican.jinja-filters
Requires-Dist: reyaml
Requires-Dist: parsedatetime (>=1.5)
Requires-Dist: pytz (>=2015.7)
Requires-Dist: six (>=1.10.0)
Requires-Dist: cryptography (<2.0,>=1.4)
Requires-Dist: tzlocal (>=1.2)
Requires-Dist: pyyaml (>=3.11)
Requires-Dist: keyring (>=7.3)
Requires-Dist: passlib (>=1.6.2)
Requires-Dist: pyxdg (>=0.25)
Requires-Dist: asteval (>=0.9.8)
Requires-Dist: python-dateutil (==1.5); python_version == '2.6'
Requires-Dist: python-dateutil (==1.5); python_version == '2.7'
Requires-Dist: python-dateutil (>=2.2); python_version >= '3.0'
Requires-Dist: monotonic; python_version<'3.3'
Requires-Dist: readline (>=6.2); sys_platform != 'win32'
Requires-Dist: pyreadline (>=2.0); sys_platform == 'win32'
Requires-Dist: colorama (>=0.2.5); sys_platform == 'win32'
Provides-Extra: all
Requires-Dist: monotonic; extra == 'all'
Requires-Dist: pyreadline (>=2.0); extra == 'all'
Requires-Dist: colorama (>=0.2.5); extra == 'all'
Requires-Dist: readline (>=6.2); extra == 'all'
Requires-Dist: python-dateutil (==1.5); extra == 'all'
Requires-Dist: python-dateutil (==1.5); extra == 'all'
Requires-Dist: python-dateutil (>=2.2); extra == 'all'
Requires-Dist: releases; extra == 'all'
Requires-Dist: green; extra == 'all'
Requires-Dist: pip-tools; extra == 'all'
Requires-Dist: minchin.releaser; extra == 'all'
Requires-Dist: check-manifest; extra == 'all'
Provides-Extra: build
Requires-Dist: releases; extra == 'build'
Requires-Dist: green; extra == 'build'
Requires-Dist: pip-tools; extra == 'build'
Requires-Dist: minchin.releaser; extra == 'build'
Requires-Dist: check-manifest; extra == 'build'
Provides-Extra: docs
Provides-Extra: test
